Metadata-Version: 1.1
Name: Flask-Color
Version: 0.2
Summary: flask-color is an extension for Flask that improves the built-in web server with colors when debugging. Unnecessary clutter such as time or IP are hidden.
Home-page: https://github.com/Frozenball/flask-color
Author: Frozenball
Author-email: orkkiolento@gmail.com
License: MIT
Platform: any
Classifier: Development Status :: 4 - Beta
Classifier: Environment :: Web Environment
Classifier: Intended Audience :: Developers
Classifier: License :: OSI Approved :: MIT License
Classifier: Operating System :: OS Independent
Classifier: Programming Language :: Python
Classifier: Topic :: Internet :: WWW/HTTP :: Dynamic Content
Classifier: Topic :: Software Development :: Libraries :: Python Modules
